README.md
setup.py
data/__init__.py
plantflow/__init__.py
plantflow/analysis.py
plantflow/plantflow.py
plantflow/utils.py
plantflow/version.py
plantflow/weibull.py
plantflow/wonka.py
plantflow.egg-info/PKG-INFO
plantflow.egg-info/SOURCES.txt
plantflow.egg-info/dependency_links.txt
plantflow.egg-info/requires.txt
plantflow.egg-info/top_level.txt