Metadata-Version: 1.2
Name: plantflow
Version: 0.0
Summary: PlantFlow: for simulating and analyzing chemical and manufacturing plant data
Home-page: http://github.com/wesleybeckner/plantflow
Author: Wesley Beckner
Author-email: wesleybeckner@gmail.com
Maintainer: Wesley Beckner
Maintainer-email: wesleybeckner@gmail.com
License: MIT
Platform: OS Independent
Classifier: Development Status :: 3 - Alpha
Classifier: Environment :: Console
Classifier: Intended Audience :: Science/Research
Classifier: License :: OSI Approved :: MIT License
Classifier: Operating System :: OS Independent
Classifier: Programming Language :: Python
Classifier: Topic :: Scientific/Engineering
Requires: numpy
